Workbook
Name Channels: 'Lists'!$A$2:$A$7
Name Offers: 'Lists'!$B$2:$B$7
Name Stages: 'Lists'!$C$2:$C$13
Name ActivityTypes: 'Lists'!$D$2:$D$14
Name Probabilities: 'Lists'!$E$2:$E$8

Sheet Dashboard
A1: Kepler Dev — Sales Dashboard
A2: Controlled-launch performance, funnel health, and pipeline visibility
A4: Reporting start | B4: 46244 | F4: Open weighted pipeline | G4: =SUM(Leads!$AA$6:$AA$205)
A5: Reporting end | B5: 46271
F6: Overdue next actions | G6: =COUNTIFS(Leads!$Y$6:$Y$205,"<"&TODAY(),Leads!$Y$6:$Y$205,"<>",Leads!$V$6:$V$205,"<>Won",Leads!$V$6:$V$205,"<>Lost/Rejected")
A7: CONTROLLED-LAUNCH TARGETS
A8: Metric | B8: Actual | C8: Target | D8: Progress
A9: Researched GCC accounts | B9: =COUNTIFS(Leads!$B$6:$B$205,">="&$B$4,Leads!$B$6:$B$205,"<="&$B$5,Leads!$H$6:$H$205,"GCC Direct") | C9: 30 | D9: =IFERROR(B9/C9,0)
A10: Upwork proposals sent | B10: =COUNTIFS(Activities!$B$6:$B$405,">="&$B$4,Activities!$B$6:$B$405,"<="&$B$5,Activities!$E$6:$E$405,"Upwork Proposal") | C10: 20 | D10: =IFERROR(B10/C10,0)
A11: Personalized GCC messages | B11: =COUNTIFS(Activities!$B$6:$B$405,">="&$B$4,Activities!$B$6:$B$405,"<="&$B$5,Activities!$E$6:$E$405,"GCC Outreach") | C11: 15 | D11: =IFERROR(B11/C11,0)
A12: Warm introduction requests | B12: =COUNTIFS(Activities!$B$6:$B$405,">="&$B$4,Activities!$B$6:$B$405,"<="&$B$5,Activities!$E$6:$E$405,"Warm Introduction Request") | C12: 10 | D12: =IFERROR(B12/C12,0)
A13: Qualified discovery calls | B13: =COUNTIFS(Activities!$B$6:$B$405,">="&$B$4,Activities!$B$6:$B$405,"<="&$B$5,Activities!$E$6:$E$405,"Discovery Call Completed",Activities!$H$6:$H$405,"Yes") | C13: 5 | D13: =IFERROR(B13/C13,0)
A14: Blueprint proposals | B14: =COUNTIFS(Activities!$B$6:$B$405,">="&$B$4,Activities!$B$6:$B$405,"<="&$B$5,Activities!$E$6:$E$405,"Blueprint Proposed") | C14: 2 | D14: =IFERROR(B14/C14,0)
A15: Build proposals | B15: =COUNTIFS(Activities!$B$6:$B$405,">="&$B$4,Activities!$B$6:$B$405,"<="&$B$5,Activities!$E$6:$E$405,"Build Proposal Sent") | C15: 1 | D15: =IFERROR(B15/C15,0)
A16: Contracts won | B16: =COUNTIFS(Activities!$B$6:$B$405,">="&$B$4,Activities!$B$6:$B$405,"<="&$B$5,Activities!$E$6:$E$405,"Contract Won") | C16: 1 | D16: =IFERROR(B16/C16,0)
A17: Collected cash (USD) | B17: =SUMIFS(Activities!$I$6:$I$405,Activities!$B$6:$B$405,">="&$B$4,Activities!$B$6:$B$405,"<="&$B$5,Activities!$E$6:$E$405,"Payment Collected") | C17: 2000 | D17: =IFERROR(B17/C17,0)
A20: FUNNEL AND PIPELINE
A21: Funnel step | B21: Count | C21: Conversion | D21: Interpretation
A22: First contacts | B22: =COUNTIFS(Activities!$B$6:$B$405,">="&$B$4,Activities!$B$6:$B$405,"<="&$B$5,Activities!$E$6:$E$405,"Upwork Proposal")+COUNTIFS(Activities!$B$6:$B$405,">="&$B$4,Activities!$B$6:$B$405,"<="&$B$5,Activities!$E$6:$E$405,"GCC Outreach")+COUNTIFS(Activities!$B$6:$B$405,">="&$B$4,Activities!$B$6:$B$405,"<="&$B$5,Activities!$E$6:$E$405,"Warm Introduction Request") | D22: Activity volume
A23: Replies | B23: =COUNTIFS(Activities!$B$6:$B$405,">="&$B$4,Activities!$B$6:$B$405,"<="&$B$5,Activities!$E$6:$E$405,"Reply Received") | C23: =IFERROR(B23/B22,0) | D23: Message-market response
A24: Qualified replies | B24: =COUNTIFS(Activities!$B$6:$B$405,">="&$B$4,Activities!$B$6:$B$405,"<="&$B$5,Activities!$E$6:$E$405,"Reply Received",Activities!$H$6:$H$405,"Yes") | C24: =IFERROR(B24/B23,0) | D24: Lead quality
A25: Discovery calls | B25: =COUNTIFS(Activities!$B$6:$B$405,">="&$B$4,Activities!$B$6:$B$405,"<="&$B$5,Activities!$E$6:$E$405,"Discovery Call Completed") | C25: =IFERROR(B25/B24,0) | D25: Qualification to conversation
A26: Paid offers proposed | B26: =COUNTIFS(Activities!$B$6:$B$405,">="&$B$4,Activities!$B$6:$B$405,"<="&$B$5,Activities!$E$6:$E$405,"Blueprint Proposed")+COUNTIFS(Activities!$B$6:$B$405,">="&$B$4,Activities!$B$6:$B$405,"<="&$B$5,Activities!$E$6:$E$405,"Build Proposal Sent") | C26: =IFERROR(B26/B25,0) | D26: Call to commercial next step
A27: Contracts won | B27: =COUNTIFS(Activities!$B$6:$B$405,">="&$B$4,Activities!$B$6:$B$405,"<="&$B$5,Activities!$E$6:$E$405,"Contract Won") | C27: =IFERROR(B27/B26,0) | D27: Offer conversion

Sheet Leads
A1: Kepler Dev — Lead Tracker
A2: One row per company, job, or opportunity
A4: Enter facts in white/yellow cells. Score each opportunity 0–2; Total, Recommendation, and Weighted Pipeline calculate automatically.
A5: Lead ID | B5: Created Date | C5: Company / Opportunity | D5: Contact Name | E5: Role | F5: Country | G5: Sector | H5: Channel | I5: Source URL | J5: Problem Hypothesis | K5: Relevant Offer | L5: Estimated Value USD | M5: Capability Fit (0-2) | N5: Budget (0-2) | O5: Scope Clarity (0-2) | P5: Client History (0-2) | Q5: Decision Quality (0-2) | R5: Proof Match (0-2) | S5: Timing (0-2) | T5: Total Score | U5: Recommendation | V5: Stage | W5: Last Activity | X5: Next Action | Y5: Next Action Date | Z5: Probability | AA5: Weighted Pipeline USD | AB5: Outcome / Loss Reason | AC5: Notes
T6: =IF(COUNTA(M6:S6)=0,"",SUM(M6:S6)) | U6: =IF(T6="","",IF(T6>=10,"Apply/Pursue",IF(T6=9,"Review","Reject"))) | AA6: =IF(OR(L6="",Z6=""),"",L6*Z6)
T7: =IF(COUNTA(M7:S7)=0,"",SUM(M7:S7)) | U7: =IF(T7="","",IF(T7>=10,"Apply/Pursue",IF(T7=9,"Review","Reject"))) | AA7: =IF(OR(L7="",Z7=""),"",L7*Z7)
T8: =IF(COUNTA(M8:S8)=0,"",SUM(M8:S8)) | U8: =IF(T8="","",IF(T8>=10,"Apply/Pursue",IF(T8=9,"Review","Reject"))) | AA8: =IF(OR(L8="",Z8=""),"",L8*Z8)
T9: =IF(COUNTA(M9:S9)=0,"",SUM(M9:S9)) | U9: =IF(T9="","",IF(T9>=10,"Apply/Pursue",IF(T9=9,"Review","Reject"))) | AA9: =IF(OR(L9="",Z9=""),"",L9*Z9)
T10: =IF(COUNTA(M10:S10)=0,"",SUM(M10:S10)) | U10: =IF(T10="","",IF(T10>=10,"Apply/Pursue",IF(T10=9,"Review","Reject"))) | AA10: =IF(OR(L10="",Z10=""),"",L10*Z10)
T11: =IF(COUNTA(M11:S11)=0,"",SUM(M11:S11)) | U11: =IF(T11="","",IF(T11>=10,"Apply/Pursue",IF(T11=9,"Review","Reject"))) | AA11: =IF(OR(L11="",Z11=""),"",L11*Z11)
T12: =IF(COUNTA(M12:S12)=0,"",SUM(M12:S12)) | U12: =IF(T12="","",IF(T12>=10,"Apply/Pursue",IF(T12=9,"Review","Reject"))) | AA12: =IF(OR(L12="",Z12=""),"",L12*Z12)
T13: =IF(COUNTA(M13:S13)=0,"",SUM(M13:S13)) | U13: =IF(T13="","",IF(T13>=10,"Apply/Pursue",IF(T13=9,"Review","Reject"))) | AA13: =IF(OR(L13="",Z13=""),"",L13*Z13)
T14: =IF(COUNTA(M14:S14)=0,"",SUM(M14:S14)) | U14: =IF(T14="","",IF(T14>=10,"Apply/Pursue",IF(T14=9,"Review","Reject"))) | AA14: =IF(OR(L14="",Z14=""),"",L14*Z14)
T15: =IF(COUNTA(M15:S15)=0,"",SUM(M15:S15)) | U15: =IF(T15="","",IF(T15>=10,"Apply/Pursue",IF(T15=9,"Review","Reject"))) | AA15: =IF(OR(L15="",Z15=""),"",L15*Z15)
T16: =IF(COUNTA(M16:S16)=0,"",SUM(M16:S16)) | U16: =IF(T16="","",IF(T16>=10,"Apply/Pursue",IF(T16=9,"Review","Reject"))) | AA16: =IF(OR(L16="",Z16=""),"",L16*Z16)
T17: =IF(COUNTA(M17:S17)=0,"",SUM(M17:S17)) | U17: =IF(T17="","",IF(T17>=10,"Apply/Pursue",IF(T17=9,"Review","Reject"))) | AA17: =IF(OR(L17="",Z17=""),"",L17*Z17)
... T205: =IF(COUNTA(M205:S205)=0,"",SUM(M205:S205)) | U205: =IF(T205="","",IF(T205>=10,"Apply/Pursue",IF(T205=9,"Review","Reject"))) | AA205: =IF(OR(L205="",Z205=""),"",L205*Z205)

Sheet Activities
A1: Kepler Dev — Sales Activities
A2: One row per contact, reply, call, proposal, win, or payment
A4: Record every meaningful sales event. Dashboard and weekly metrics calculate from Activity Type, Date, Qualified Reply, and Amount.
A5: Activity ID | B5: Date | C5: Lead ID | D5: Company / Opportunity | E5: Activity Type | F5: Channel | G5: Outcome | H5: Qualified? | I5: Amount USD | J5: Next Action Date | K5: Notes

Sheet Weekly Scorecard
A1: Kepler Dev — Weekly Sales Scorecard
A2: Review every week; change the strategy only after reading the underlying conversations
A4: The first twelve weeks are preloaded. Activity metrics calculate automatically; enter the pipeline snapshot at the end of each week.
A5: Week Start | B5: GCC Accounts | C5: Upwork Proposals | D5: GCC Outreach | E5: Warm Intros | F5: Replies | G5: Qualified Replies | H5: Calls Completed | I5: Blueprints Proposed | J5: Blueprints Sold | K5: Build Proposals | L5: Wins | M5: Collected Cash USD | N5: Pipeline Snapshot USD | O5: Reply Rate | P5: Qualification Rate | Q5: Call Rate | R5: Proposal Rate | S5: Win Rate | T5: Weekly Learning / Decision
A6: 46244 | B6: =COUNTIFS(Leads!$B$6:$B$205,">="&A6,Leads!$B$6:$B$205,"<="&A6+6,Leads!$H$6:$H$205,"GCC Direct") | C6: =COUNTIFS(Activities!$B$6:$B$405,">="&A6,Activities!$B$6:$B$405,"<="&A6+6,Activities!$E$6:$E$405,"Upwork Proposal") | D6: =COUNTIFS(Activities!$B$6:$B$405,">="&A6,Activities!$B$6:$B$405,"<="&A6+6,Activities!$E$6:$E$405,"GCC Outreach") | E6: =COUNTIFS(Activities!$B$6:$B$405,">="&A6,Activities!$B$6:$B$405,"<="&A6+6,Activities!$E$6:$E$405,"Warm Introduction Request") | F6: =COUNTIFS(Activities!$B$6:$B$405,">="&A6,Activities!$B$6:$B$405,"<="&A6+6,Activities!$E$6:$E$405,"Reply Received") | G6: =COUNTIFS(Activities!$B$6:$B$405,">="&A6,Activities!$B$6:$B$405,"<="&A6+6,Activities!$E$6:$E$405,"Reply Received",Activities!$H$6:$H$405,"Yes") | H6: =COUNTIFS(Activities!$B$6:$B$405,">="&A6,Activities!$B$6:$B$405,"<="&A6+6,Activities!$E$6:$E$405,"Discovery Call Completed") | I6: =COUNTIFS(Activities!$B$6:$B$405,">="&A6,Activities!$B$6:$B$405,"<="&A6+6,Activities!$E$6:$E$405,"Blueprint Proposed") | J6: =COUNTIFS(Activities!$B$6:$B$405,">="&A6,Activities!$B$6:$B$405,"<="&A6+6,Activities!$E$6:$E$405,"Blueprint Sold") | K6: =COUNTIFS(Activities!$B$6:$B$405,">="&A6,Activities!$B$6:$B$405,"<="&A6+6,Activities!$E$6:$E$405,"Build Proposal Sent") | L6: =COUNTIFS(Activities!$B$6:$B$405,">="&A6,Activities!$B$6:$B$405,"<="&A6+6,Activities!$E$6:$E$405,"Contract Won") | M6: =SUMIFS(Activities!$I$6:$I$405,Activities!$B$6:$B$405,">="&A6,Activities!$B$6:$B$405,"<="&A6+6,Activities!$E$6:$E$405,"Payment Collected") | O6: =IFERROR(F6/SUM(C6:E6),0) | P6: =IFERROR(G6/F6,0) | Q6: =IFERROR(H6/G6,0) | R6: =IFERROR((I6+K6)/H6,0) | S6: =IFERROR(L6/(I6+K6),0)
A7: 46251 | B7: =COUNTIFS(Leads!$B$6:$B$205,">="&A7,Leads!$B$6:$B$205,"<="&A7+6,Leads!$H$6:$H$205,"GCC Direct") | C7: =COUNTIFS(Activities!$B$6:$B$405,">="&A7,Activities!$B$6:$B$405,"<="&A7+6,Activities!$E$6:$E$405,"Upwork Proposal") | D7: =COUNTIFS(Activities!$B$6:$B$405,">="&A7,Activities!$B$6:$B$405,"<="&A7+6,Activities!$E$6:$E$405,"GCC Outreach") | E7: =COUNTIFS(Activities!$B$6:$B$405,">="&A7,Activities!$B$6:$B$405,"<="&A7+6,Activities!$E$6:$E$405,"Warm Introduction Request") | F7: =COUNTIFS(Activities!$B$6:$B$405,">="&A7,Activities!$B$6:$B$405,"<="&A7+6,Activities!$E$6:$E$405,"Reply Received") | G7: =COUNTIFS(Activities!$B$6:$B$405,">="&A7,Activities!$B$6:$B$405,"<="&A7+6,Activities!$E$6:$E$405,"Reply Received",Activities!$H$6:$H$405,"Yes") | H7: =COUNTIFS(Activities!$B$6:$B$405,">="&A7,Activities!$B$6:$B$405,"<="&A7+6,Activities!$E$6:$E$405,"Discovery Call Completed") | I7: =COUNTIFS(Activities!$B$6:$B$405,">="&A7,Activities!$B$6:$B$405,"<="&A7+6,Activities!$E$6:$E$405,"Blueprint Proposed") | J7: =COUNTIFS(Activities!$B$6:$B$405,">="&A7,Activities!$B$6:$B$405,"<="&A7+6,Activities!$E$6:$E$405,"Blueprint Sold") | K7: =COUNTIFS(Activities!$B$6:$B$405,">="&A7,Activities!$B$6:$B$405,"<="&A7+6,Activities!$E$6:$E$405,"Build Proposal Sent") | L7: =COUNTIFS(Activities!$B$6:$B$405,">="&A7,Activities!$B$6:$B$405,"<="&A7+6,Activities!$E$6:$E$405,"Contract Won") | M7: =SUMIFS(Activities!$I$6:$I$405,Activities!$B$6:$B$405,">="&A7,Activities!$B$6:$B$405,"<="&A7+6,Activities!$E$6:$E$405,"Payment Collected") | O7: =IFERROR(F7/SUM(C7:E7),0) | P7: =IFERROR(G7/F7,0) | Q7: =IFERROR(H7/G7,0) | R7: =IFERROR((I7+K7)/H7,0) | S7: =IFERROR(L7/(I7+K7),0)
A8: 46258 | B8: =COUNTIFS(Leads!$B$6:$B$205,">="&A8,Leads!$B$6:$B$205,"<="&A8+6,Leads!$H$6:$H$205,"GCC Direct") | C8: =COUNTIFS(Activities!$B$6:$B$405,">="&A8,Activities!$B$6:$B$405,"<="&A8+6,Activities!$E$6:$E$405,"Upwork Proposal") | D8: =COUNTIFS(Activities!$B$6:$B$405,">="&A8,Activities!$B$6:$B$405,"<="&A8+6,Activities!$E$6:$E$405,"GCC Outreach") | E8: =COUNTIFS(Activities!$B$6:$B$405,">="&A8,Activities!$B$6:$B$405,"<="&A8+6,Activities!$E$6:$E$405,"Warm Introduction Request") | F8: =COUNTIFS(Activities!$B$6:$B$405,">="&A8,Activities!$B$6:$B$405,"<="&A8+6,Activities!$E$6:$E$405,"Reply Received") | G8: =COUNTIFS(Activities!$B$6:$B$405,">="&A8,Activities!$B$6:$B$405,"<="&A8+6,Activities!$E$6:$E$405,"Reply Received",Activities!$H$6:$H$405,"Yes") | H8: =COUNTIFS(Activities!$B$6:$B$405,">="&A8,Activities!$B$6:$B$405,"<="&A8+6,Activities!$E$6:$E$405,"Discovery Call Completed") | I8: =COUNTIFS(Activities!$B$6:$B$405,">="&A8,Activities!$B$6:$B$405,"<="&A8+6,Activities!$E$6:$E$405,"Blueprint Proposed") | J8: =COUNTIFS(Activities!$B$6:$B$405,">="&A8,Activities!$B$6:$B$405,"<="&A8+6,Activities!$E$6:$E$405,"Blueprint Sold") | K8: =COUNTIFS(Activities!$B$6:$B$405,">="&A8,Activities!$B$6:$B$405,"<="&A8+6,Activities!$E$6:$E$405,"Build Proposal Sent") | L8: =COUNTIFS(Activities!$B$6:$B$405,">="&A8,Activities!$B$6:$B$405,"<="&A8+6,Activities!$E$6:$E$405,"Contract Won") | M8: =SUMIFS(Activities!$I$6:$I$405,Activities!$B$6:$B$405,">="&A8,Activities!$B$6:$B$405,"<="&A8+6,Activities!$E$6:$E$405,"Payment Collected") | O8: =IFERROR(F8/SUM(C8:E8),0) | P8: =IFERROR(G8/F8,0) | Q8: =IFERROR(H8/G8,0) | R8: =IFERROR((I8+K8)/H8,0) | S8: =IFERROR(L8/(I8+K8),0)
A9: 46265 | B9: =COUNTIFS(Leads!$B$6:$B$205,">="&A9,Leads!$B$6:$B$205,"<="&A9+6,Leads!$H$6:$H$205,"GCC Direct") | C9: =COUNTIFS(Activities!$B$6:$B$405,">="&A9,Activities!$B$6:$B$405,"<="&A9+6,Activities!$E$6:$E$405,"Upwork Proposal") | D9: =COUNTIFS(Activities!$B$6:$B$405,">="&A9,Activities!$B$6:$B$405,"<="&A9+6,Activities!$E$6:$E$405,"GCC Outreach") | E9: =COUNTIFS(Activities!$B$6:$B$405,">="&A9,Activities!$B$6:$B$405,"<="&A9+6,Activities!$E$6:$E$405,"Warm Introduction Request") | F9: =COUNTIFS(Activities!$B$6:$B$405,">="&A9,Activities!$B$6:$B$405,"<="&A9+6,Activities!$E$6:$E$405,"Reply Received") | G9: =COUNTIFS(Activities!$B$6:$B$405,">="&A9,Activities!$B$6:$B$405,"<="&A9+6,Activities!$E$6:$E$405,"Reply Received",Activities!$H$6:$H$405,"Yes") | H9: =COUNTIFS(Activities!$B$6:$B$405,">="&A9,Activities!$B$6:$B$405,"<="&A9+6,Activities!$E$6:$E$405,"Discovery Call Completed") | I9: =COUNTIFS(Activities!$B$6:$B$405,">="&A9,Activities!$B$6:$B$405,"<="&A9+6,Activities!$E$6:$E$405,"Blueprint Proposed") | J9: =COUNTIFS(Activities!$B$6:$B$405,">="&A9,Activities!$B$6:$B$405,"<="&A9+6,Activities!$E$6:$E$405,"Blueprint Sold") | K9: =COUNTIFS(Activities!$B$6:$B$405,">="&A9,Activities!$B$6:$B$405,"<="&A9+6,Activities!$E$6:$E$405,"Build Proposal Sent") | L9: =COUNTIFS(Activities!$B$6:$B$405,">="&A9,Activities!$B$6:$B$405,"<="&A9+6,Activities!$E$6:$E$405,"Contract Won") | M9: =SUMIFS(Activities!$I$6:$I$405,Activities!$B$6:$B$405,">="&A9,Activities!$B$6:$B$405,"<="&A9+6,Activities!$E$6:$E$405,"Payment Collected") | O9: =IFERROR(F9/SUM(C9:E9),0) | P9: =IFERROR(G9/F9,0) | Q9: =IFERROR(H9/G9,0) | R9: =IFERROR((I9+K9)/H9,0) | S9: =IFERROR(L9/(I9+K9),0)
A10: 46272 | B10: =COUNTIFS(Leads!$B$6:$B$205,">="&A10,Leads!$B$6:$B$205,"<="&A10+6,Leads!$H$6:$H$205,"GCC Direct") | C10: =COUNTIFS(Activities!$B$6:$B$405,">="&A10,Activities!$B$6:$B$405,"<="&A10+6,Activities!$E$6:$E$405,"Upwork Proposal") | D10: =COUNTIFS(Activities!$B$6:$B$405,">="&A10,Activities!$B$6:$B$405,"<="&A10+6,Activities!$E$6:$E$405,"GCC Outreach") | E10: =COUNTIFS(Activities!$B$6:$B$405,">="&A10,Activities!$B$6:$B$405,"<="&A10+6,Activities!$E$6:$E$405,"Warm Introduction Request") | F10: =COUNTIFS(Activities!$B$6:$B$405,">="&A10,Activities!$B$6:$B$405,"<="&A10+6,Activities!$E$6:$E$405,"Reply Received") | G10: =COUNTIFS(Activities!$B$6:$B$405,">="&A10,Activities!$B$6:$B$405,"<="&A10+6,Activities!$E$6:$E$405,"Reply Received",Activities!$H$6:$H$405,"Yes") | H10: =COUNTIFS(Activities!$B$6:$B$405,">="&A10,Activities!$B$6:$B$405,"<="&A10+6,Activities!$E$6:$E$405,"Discovery Call Completed") | I10: =COUNTIFS(Activities!$B$6:$B$405,">="&A10,Activities!$B$6:$B$405,"<="&A10+6,Activities!$E$6:$E$405,"Blueprint Proposed") | J10: =COUNTIFS(Activities!$B$6:$B$405,">="&A10,Activities!$B$6:$B$405,"<="&A10+6,Activities!$E$6:$E$405,"Blueprint Sold") | K10: =COUNTIFS(Activities!$B$6:$B$405,">="&A10,Activities!$B$6:$B$405,"<="&A10+6,Activities!$E$6:$E$405,"Build Proposal Sent") | L10: =COUNTIFS(Activities!$B$6:$B$405,">="&A10,Activities!$B$6:$B$405,"<="&A10+6,Activities!$E$6:$E$405,"Contract Won") | M10: =SUMIFS(Activities!$I$6:$I$405,Activities!$B$6:$B$405,">="&A10,Activities!$B$6:$B$405,"<="&A10+6,Activities!$E$6:$E$405,"Payment Collected") | O10: =IFERROR(F10/SUM(C10:E10),0) | P10: =IFERROR(G10/F10,0) | Q10: =IFERROR(H10/G10,0) | R10: =IFERROR((I10+K10)/H10,0) | S10: =IFERROR(L10/(I10+K10),0)
A11: 46279 | B11: =COUNTIFS(Leads!$B$6:$B$205,">="&A11,Leads!$B$6:$B$205,"<="&A11+6,Leads!$H$6:$H$205,"GCC Direct") | C11: =COUNTIFS(Activities!$B$6:$B$405,">="&A11,Activities!$B$6:$B$405,"<="&A11+6,Activities!$E$6:$E$405,"Upwork Proposal") | D11: =COUNTIFS(Activities!$B$6:$B$405,">="&A11,Activities!$B$6:$B$405,"<="&A11+6,Activities!$E$6:$E$405,"GCC Outreach") | E11: =COUNTIFS(Activities!$B$6:$B$405,">="&A11,Activities!$B$6:$B$405,"<="&A11+6,Activities!$E$6:$E$405,"Warm Introduction Request") | F11: =COUNTIFS(Activities!$B$6:$B$405,">="&A11,Activities!$B$6:$B$405,"<="&A11+6,Activities!$E$6:$E$405,"Reply Received") | G11: =COUNTIFS(Activities!$B$6:$B$405,">="&A11,Activities!$B$6:$B$405,"<="&A11+6,Activities!$E$6:$E$405,"Reply Received",Activities!$H$6:$H$405,"Yes") | H11: =COUNTIFS(Activities!$B$6:$B$405,">="&A11,Activities!$B$6:$B$405,"<="&A11+6,Activities!$E$6:$E$405,"Discovery Call Completed") | I11: =COUNTIFS(Activities!$B$6:$B$405,">="&A11,Activities!$B$6:$B$405,"<="&A11+6,Activities!$E$6:$E$405,"Blueprint Proposed") | J11: =COUNTIFS(Activities!$B$6:$B$405,">="&A11,Activities!$B$6:$B$405,"<="&A11+6,Activities!$E$6:$E$405,"Blueprint Sold") | K11: =COUNTIFS(Activities!$B$6:$B$405,">="&A11,Activities!$B$6:$B$405,"<="&A11+6,Activities!$E$6:$E$405,"Build Proposal Sent") | L11: =COUNTIFS(Activities!$B$6:$B$405,">="&A11,Activities!$B$6:$B$405,"<="&A11+6,Activities!$E$6:$E$405,"Contract Won") | M11: =SUMIFS(Activities!$I$6:$I$405,Activities!$B$6:$B$405,">="&A11,Activities!$B$6:$B$405,"<="&A11+6,Activities!$E$6:$E$405,"Payment Collected") | O11: =IFERROR(F11/SUM(C11:E11),0) | P11: =IFERROR(G11/F11,0) | Q11: =IFERROR(H11/G11,0) | R11: =IFERROR((I11+K11)/H11,0) | S11: =IFERROR(L11/(I11+K11),0)
A12: 46286 | B12: =COUNTIFS(Leads!$B$6:$B$205,">="&A12,Leads!$B$6:$B$205,"<="&A12+6,Leads!$H$6:$H$205,"GCC Direct") | C12: =COUNTIFS(Activities!$B$6:$B$405,">="&A12,Activities!$B$6:$B$405,"<="&A12+6,Activities!$E$6:$E$405,"Upwork Proposal") | D12: =COUNTIFS(Activities!$B$6:$B$405,">="&A12,Activities!$B$6:$B$405,"<="&A12+6,Activities!$E$6:$E$405,"GCC Outreach") | E12: =COUNTIFS(Activities!$B$6:$B$405,">="&A12,Activities!$B$6:$B$405,"<="&A12+6,Activities!$E$6:$E$405,"Warm Introduction Request") | F12: =COUNTIFS(Activities!$B$6:$B$405,">="&A12,Activities!$B$6:$B$405,"<="&A12+6,Activities!$E$6:$E$405,"Reply Received") | G12: =COUNTIFS(Activities!$B$6:$B$405,">="&A12,Activities!$B$6:$B$405,"<="&A12+6,Activities!$E$6:$E$405,"Reply Received",Activities!$H$6:$H$405,"Yes") | H12: =COUNTIFS(Activities!$B$6:$B$405,">="&A12,Activities!$B$6:$B$405,"<="&A12+6,Activities!$E$6:$E$405,"Discovery Call Completed") | I12: =COUNTIFS(Activities!$B$6:$B$405,">="&A12,Activities!$B$6:$B$405,"<="&A12+6,Activities!$E$6:$E$405,"Blueprint Proposed") | J12: =COUNTIFS(Activities!$B$6:$B$405,">="&A12,Activities!$B$6:$B$405,"<="&A12+6,Activities!$E$6:$E$405,"Blueprint Sold") | K12: =COUNTIFS(Activities!$B$6:$B$405,">="&A12,Activities!$B$6:$B$405,"<="&A12+6,Activities!$E$6:$E$405,"Build Proposal Sent") | L12: =COUNTIFS(Activities!$B$6:$B$405,">="&A12,Activities!$B$6:$B$405,"<="&A12+6,Activities!$E$6:$E$405,"Contract Won") | M12: =SUMIFS(Activities!$I$6:$I$405,Activities!$B$6:$B$405,">="&A12,Activities!$B$6:$B$405,"<="&A12+6,Activities!$E$6:$E$405,"Payment Collected") | O12: =IFERROR(F12/SUM(C12:E12),0) | P12: =IFERROR(G12/F12,0) | Q12: =IFERROR(H12/G12,0) | R12: =IFERROR((I12+K12)/H12,0) | S12: =IFERROR(L12/(I12+K12),0)
A13: 46293 | B13: =COUNTIFS(Leads!$B$6:$B$205,">="&A13,Leads!$B$6:$B$205,"<="&A13+6,Leads!$H$6:$H$205,"GCC Direct") | C13: =COUNTIFS(Activities!$B$6:$B$405,">="&A13,Activities!$B$6:$B$405,"<="&A13+6,Activities!$E$6:$E$405,"Upwork Proposal") | D13: =COUNTIFS(Activities!$B$6:$B$405,">="&A13,Activities!$B$6:$B$405,"<="&A13+6,Activities!$E$6:$E$405,"GCC Outreach") | E13: =COUNTIFS(Activities!$B$6:$B$405,">="&A13,Activities!$B$6:$B$405,"<="&A13+6,Activities!$E$6:$E$405,"Warm Introduction Request") | F13: =COUNTIFS(Activities!$B$6:$B$405,">="&A13,Activities!$B$6:$B$405,"<="&A13+6,Activities!$E$6:$E$405,"Reply Received") | G13: =COUNTIFS(Activities!$B$6:$B$405,">="&A13,Activities!$B$6:$B$405,"<="&A13+6,Activities!$E$6:$E$405,"Reply Received",Activities!$H$6:$H$405,"Yes") | H13: =COUNTIFS(Activities!$B$6:$B$405,">="&A13,Activities!$B$6:$B$405,"<="&A13+6,Activities!$E$6:$E$405,"Discovery Call Completed") | I13: =COUNTIFS(Activities!$B$6:$B$405,">="&A13,Activities!$B$6:$B$405,"<="&A13+6,Activities!$E$6:$E$405,"Blueprint Proposed") | J13: =COUNTIFS(Activities!$B$6:$B$405,">="&A13,Activities!$B$6:$B$405,"<="&A13+6,Activities!$E$6:$E$405,"Blueprint Sold") | K13: =COUNTIFS(Activities!$B$6:$B$405,">="&A13,Activities!$B$6:$B$405,"<="&A13+6,Activities!$E$6:$E$405,"Build Proposal Sent") | L13: =COUNTIFS(Activities!$B$6:$B$405,">="&A13,Activities!$B$6:$B$405,"<="&A13+6,Activities!$E$6:$E$405,"Contract Won") | M13: =SUMIFS(Activities!$I$6:$I$405,Activities!$B$6:$B$405,">="&A13,Activities!$B$6:$B$405,"<="&A13+6,Activities!$E$6:$E$405,"Payment Collected") | O13: =IFERROR(F13/SUM(C13:E13),0) | P13: =IFERROR(G13/F13,0) | Q13: =IFERROR(H13/G13,0) | R13: =IFERROR((I13+K13)/H13,0) | S13: =IFERROR(L13/(I13+K13),0)
A14: 46300 | B14: =COUNTIFS(Leads!$B$6:$B$205,">="&A14,Leads!$B$6:$B$205,"<="&A14+6,Leads!$H$6:$H$205,"GCC Direct") | C14: =COUNTIFS(Activities!$B$6:$B$405,">="&A14,Activities!$B$6:$B$405,"<="&A14+6,Activities!$E$6:$E$405,"Upwork Proposal") | D14: =COUNTIFS(Activities!$B$6:$B$405,">="&A14,Activities!$B$6:$B$405,"<="&A14+6,Activities!$E$6:$E$405,"GCC Outreach") | E14: =COUNTIFS(Activities!$B$6:$B$405,">="&A14,Activities!$B$6:$B$405,"<="&A14+6,Activities!$E$6:$E$405,"Warm Introduction Request") | F14: =COUNTIFS(Activities!$B$6:$B$405,">="&A14,Activities!$B$6:$B$405,"<="&A14+6,Activities!$E$6:$E$405,"Reply Received") | G14: =COUNTIFS(Activities!$B$6:$B$405,">="&A14,Activities!$B$6:$B$405,"<="&A14+6,Activities!$E$6:$E$405,"Reply Received",Activities!$H$6:$H$405,"Yes") | H14: =COUNTIFS(Activities!$B$6:$B$405,">="&A14,Activities!$B$6:$B$405,"<="&A14+6,Activities!$E$6:$E$405,"Discovery Call Completed") | I14: =COUNTIFS(Activities!$B$6:$B$405,">="&A14,Activities!$B$6:$B$405,"<="&A14+6,Activities!$E$6:$E$405,"Blueprint Proposed") | J14: =COUNTIFS(Activities!$B$6:$B$405,">="&A14,Activities!$B$6:$B$405,"<="&A14+6,Activities!$E$6:$E$405,"Blueprint Sold") | K14: =COUNTIFS(Activities!$B$6:$B$405,">="&A14,Activities!$B$6:$B$405,"<="&A14+6,Activities!$E$6:$E$405,"Build Proposal Sent") | L14: =COUNTIFS(Activities!$B$6:$B$405,">="&A14,Activities!$B$6:$B$405,"<="&A14+6,Activities!$E$6:$E$405,"Contract Won") | M14: =SUMIFS(Activities!$I$6:$I$405,Activities!$B$6:$B$405,">="&A14,Activities!$B$6:$B$405,"<="&A14+6,Activities!$E$6:$E$405,"Payment Collected") | O14: =IFERROR(F14/SUM(C14:E14),0) | P14: =IFERROR(G14/F14,0) | Q14: =IFERROR(H14/G14,0) | R14: =IFERROR((I14+K14)/H14,0) | S14: =IFERROR(L14/(I14+K14),0)
A15: 46307 | B15: =COUNTIFS(Leads!$B$6:$B$205,">="&A15,Leads!$B$6:$B$205,"<="&A15+6,Leads!$H$6:$H$205,"GCC Direct") | C15: =COUNTIFS(Activities!$B$6:$B$405,">="&A15,Activities!$B$6:$B$405,"<="&A15+6,Activities!$E$6:$E$405,"Upwork Proposal") | D15: =COUNTIFS(Activities!$B$6:$B$405,">="&A15,Activities!$B$6:$B$405,"<="&A15+6,Activities!$E$6:$E$405,"GCC Outreach") | E15: =COUNTIFS(Activities!$B$6:$B$405,">="&A15,Activities!$B$6:$B$405,"<="&A15+6,Activities!$E$6:$E$405,"Warm Introduction Request") | F15: =COUNTIFS(Activities!$B$6:$B$405,">="&A15,Activities!$B$6:$B$405,"<="&A15+6,Activities!$E$6:$E$405,"Reply Received") | G15: =COUNTIFS(Activities!$B$6:$B$405,">="&A15,Activities!$B$6:$B$405,"<="&A15+6,Activities!$E$6:$E$405,"Reply Received",Activities!$H$6:$H$405,"Yes") | H15: =COUNTIFS(Activities!$B$6:$B$405,">="&A15,Activities!$B$6:$B$405,"<="&A15+6,Activities!$E$6:$E$405,"Discovery Call Completed") | I15: =COUNTIFS(Activities!$B$6:$B$405,">="&A15,Activities!$B$6:$B$405,"<="&A15+6,Activities!$E$6:$E$405,"Blueprint Proposed") | J15: =COUNTIFS(Activities!$B$6:$B$405,">="&A15,Activities!$B$6:$B$405,"<="&A15+6,Activities!$E$6:$E$405,"Blueprint Sold") | K15: =COUNTIFS(Activities!$B$6:$B$405,">="&A15,Activities!$B$6:$B$405,"<="&A15+6,Activities!$E$6:$E$405,"Build Proposal Sent") | L15: =COUNTIFS(Activities!$B$6:$B$405,">="&A15,Activities!$B$6:$B$405,"<="&A15+6,Activities!$E$6:$E$405,"Contract Won") | M15: =SUMIFS(Activities!$I$6:$I$405,Activities!$B$6:$B$405,">="&A15,Activities!$B$6:$B$405,"<="&A15+6,Activities!$E$6:$E$405,"Payment Collected") | O15: =IFERROR(F15/SUM(C15:E15),0) | P15: =IFERROR(G15/F15,0) | Q15: =IFERROR(H15/G15,0) | R15: =IFERROR((I15+K15)/H15,0) | S15: =IFERROR(L15/(I15+K15),0)
A16: 46314 | B16: =COUNTIFS(Leads!$B$6:$B$205,">="&A16,Leads!$B$6:$B$205,"<="&A16+6,Leads!$H$6:$H$205,"GCC Direct") | C16: =COUNTIFS(Activities!$B$6:$B$405,">="&A16,Activities!$B$6:$B$405,"<="&A16+6,Activities!$E$6:$E$405,"Upwork Proposal") | D16: =COUNTIFS(Activities!$B$6:$B$405,">="&A16,Activities!$B$6:$B$405,"<="&A16+6,Activities!$E$6:$E$405,"GCC Outreach") | E16: =COUNTIFS(Activities!$B$6:$B$405,">="&A16,Activities!$B$6:$B$405,"<="&A16+6,Activities!$E$6:$E$405,"Warm Introduction Request") | F16: =COUNTIFS(Activities!$B$6:$B$405,">="&A16,Activities!$B$6:$B$405,"<="&A16+6,Activities!$E$6:$E$405,"Reply Received") | G16: =COUNTIFS(Activities!$B$6:$B$405,">="&A16,Activities!$B$6:$B$405,"<="&A16+6,Activities!$E$6:$E$405,"Reply Received",Activities!$H$6:$H$405,"Yes") | H16: =COUNTIFS(Activities!$B$6:$B$405,">="&A16,Activities!$B$6:$B$405,"<="&A16+6,Activities!$E$6:$E$405,"Discovery Call Completed") | I16: =COUNTIFS(Activities!$B$6:$B$405,">="&A16,Activities!$B$6:$B$405,"<="&A16+6,Activities!$E$6:$E$405,"Blueprint Proposed") | J16: =COUNTIFS(Activities!$B$6:$B$405,">="&A16,Activities!$B$6:$B$405,"<="&A16+6,Activities!$E$6:$E$405,"Blueprint Sold") | K16: =COUNTIFS(Activities!$B$6:$B$405,">="&A16,Activities!$B$6:$B$405,"<="&A16+6,Activities!$E$6:$E$405,"Build Proposal Sent") | L16: =COUNTIFS(Activities!$B$6:$B$405,">="&A16,Activities!$B$6:$B$405,"<="&A16+6,Activities!$E$6:$E$405,"Contract Won") | M16: =SUMIFS(Activities!$I$6:$I$405,Activities!$B$6:$B$405,">="&A16,Activities!$B$6:$B$405,"<="&A16+6,Activities!$E$6:$E$405,"Payment Collected") | O16: =IFERROR(F16/SUM(C16:E16),0) | P16: =IFERROR(G16/F16,0) | Q16: =IFERROR(H16/G16,0) | R16: =IFERROR((I16+K16)/H16,0) | S16: =IFERROR(L16/(I16+K16),0)
A17: 46321 | B17: =COUNTIFS(Leads!$B$6:$B$205,">="&A17,Leads!$B$6:$B$205,"<="&A17+6,Leads!$H$6:$H$205,"GCC Direct") | C17: =COUNTIFS(Activities!$B$6:$B$405,">="&A17,Activities!$B$6:$B$405,"<="&A17+6,Activities!$E$6:$E$405,"Upwork Proposal") | D17: =COUNTIFS(Activities!$B$6:$B$405,">="&A17,Activities!$B$6:$B$405,"<="&A17+6,Activities!$E$6:$E$405,"GCC Outreach") | E17: =COUNTIFS(Activities!$B$6:$B$405,">="&A17,Activities!$B$6:$B$405,"<="&A17+6,Activities!$E$6:$E$405,"Warm Introduction Request") | F17: =COUNTIFS(Activities!$B$6:$B$405,">="&A17,Activities!$B$6:$B$405,"<="&A17+6,Activities!$E$6:$E$405,"Reply Received") | G17: =COUNTIFS(Activities!$B$6:$B$405,">="&A17,Activities!$B$6:$B$405,"<="&A17+6,Activities!$E$6:$E$405,"Reply Received",Activities!$H$6:$H$405,"Yes") | H17: =COUNTIFS(Activities!$B$6:$B$405,">="&A17,Activities!$B$6:$B$405,"<="&A17+6,Activities!$E$6:$E$405,"Discovery Call Completed") | I17: =COUNTIFS(Activities!$B$6:$B$405,">="&A17,Activities!$B$6:$B$405,"<="&A17+6,Activities!$E$6:$E$405,"Blueprint Proposed") | J17: =COUNTIFS(Activities!$B$6:$B$405,">="&A17,Activities!$B$6:$B$405,"<="&A17+6,Activities!$E$6:$E$405,"Blueprint Sold") | K17: =COUNTIFS(Activities!$B$6:$B$405,">="&A17,Activities!$B$6:$B$405,"<="&A17+6,Activities!$E$6:$E$405,"Build Proposal Sent") | L17: =COUNTIFS(Activities!$B$6:$B$405,">="&A17,Activities!$B$6:$B$405,"<="&A17+6,Activities!$E$6:$E$405,"Contract Won") | M17: =SUMIFS(Activities!$I$6:$I$405,Activities!$B$6:$B$405,">="&A17,Activities!$B$6:$B$405,"<="&A17+6,Activities!$E$6:$E$405,"Payment Collected") | O17: =IFERROR(F17/SUM(C17:E17),0) | P17: =IFERROR(G17/F17,0) | Q17: =IFERROR(H17/G17,0) | R17: =IFERROR((I17+K17)/H17,0) | S17: =IFERROR(L17/(I17+K17),0)

Sheet Instructions
A1: Kepler Dev — Workbook Guide
A2: How to use the tracker without corrupting the reporting
A4: WORKFLOW
A5: 1. Leads | B5: Create one row for each Upwork job, company, referral, or other opportunity. Do not create a new row for every interaction.
A6: 2. Scoring | B6: Score all seven qualification dimensions from 0 to 2. Pursue at 10–14, review at 9, and reject below 9 unless a documented exception exists.
A7: 3. Activities | B7: Record every proposal, outreach message, reply, call, offer, win, and collected payment. Dashboards calculate from exact Activity Type labels.
A8: 4. Qualified reply | B8: Mark Yes only when a reply shows a real problem, plausible authority/access, budget or discovery willingness, and realistic timing.
A9: 5. Amount USD | B9: Use Amount only for Payment Collected and other events where a real dollar amount belongs. Do not count a verbal agreement as revenue.
A10: 6. Pipeline | B10: Estimated Value × Probability produces weighted pipeline. Set probability to 0% for lost/rejected leads and 100% only for won/funded work.
A11: 7. Next actions | B11: Every active lead needs one clear next action and date. Overdue actions appear on the Dashboard.
A12: 8. Weekly review | B12: At the end of each week, enter the open pipeline snapshot and write one evidence-based learning or decision. Avoid changing several variables simultaneously.
A13: 9. Dashboard period | B13: Change the yellow Reporting start and Reporting end cells to review any period.
A14: 10. Truthfulness | B14: Record observed facts separately from hypotheses. Track actual collected cash, not hopeful revenue.
A17: FIRST CONTROLLED-LAUNCH TARGETS
A18: 1 | B18: 20 selective Upwork proposals
A19: 2 | B19: 30 researched GCC accounts
A20: 3 | B20: 15 personalized GCC messages
A21: 4 | B21: 10 warm introduction requests
A22: 5 | B22: 5 qualified discovery calls
A23: 6 | B23: 2 Blueprint proposals
A24: 7 | B24: 1 build proposal
A25: 8 | B25: $2,000 collected-cash milestone

Sheet Lists
A1: Channels | B1: Offers | C1: Stages | D1: ActivityTypes | E1: Probabilities
A2: Upwork | B2: Product Blueprint | C2: Identified | D2: Upwork Proposal | E2: 0
A3: GCC Direct | B3: Launch Sprint | C3: Researched | D3: GCC Outreach | E3: 0.1
A4: Warm Referral | B4: Operations Platform | C4: Contacted/Applied | D4: Warm Introduction Request | E4: 0.25
A5: Egypt Local | B5: Product Care | C5: Replied | D5: Follow-up | E5: 0.5
A6: Website | B6: Technical Pilot | C6: Qualified | D6: Reply Received | E6: 0.75
A7: Other | B7: Not Yet Known | C7: Discovery Scheduled | D7: Discovery Call Scheduled | E7: 0.9
C8: Blueprint Proposed | D8: Discovery Call Completed | E8: 1
C9: Build Proposed | D9: Blueprint Proposed
C10: Verbal Agreement | D10: Blueprint Sold
C11: Won | D11: Build Proposal Sent
C12: Nurture | D12: Contract Won
C13: Lost/Rejected | D13: Payment Collected
D14: Other
